{
    "format_version": "1.12",
    "minecraft:recipe_shaped": {
      "description": {
        "identifier": "ps:cask_turtle_master"
      },
      "tags": [ "crafting_table" ],
      "pattern": [
        "SSS",
        "I I",
        "SSS"
      ],
      "key": {
        "S": {
          "item": "ps:stained_planks_turtle_master"
        },
        "I": {
          "item": "minecraft:iron_ingot"
        }
      },
      "result": {
        "item": "ps:cask_turtle_master",
        "count": 1
      }
    }
}
